omltesi/__init__.py
omltesi/preprocessing_utils.py
omltesi-0.1.0.dist-info/METADATA
omltesi-0.1.0.dist-info/WHEEL
omltesi-0.1.0.dist-info/top_level.txt
omltesi-0.1.0.dist-info/RECORD
