Metadata-Version: 2.1
Name: omltesi
Version: 0.1.0
Summary: put your description here
Home-page: UNKNOWN
License: UNKNOWN
Platform: UNKNOWN
Requires-Dist: setuptools (>=57.0.0)
